lightsqlite
