Metadata-Version: 1.2
Name: lightsqlite
Version: 0.2
Summary: The improved-package of sqlite3.
Home-page: https://github.com/Danny-Yxzl/lightsqlite
Author: Yixiangzhilv
Author-email: mail@yixiangzhilv.com
License: UNKNOWN
Project-URL: Bug Reports, https://github.com/Danny-Yxzl/lightsqlite/issues
Project-URL: Say Thanks!, https://www.yixiangzhilv.com/
Project-URL: Source, https://github.com/Danny-Yxzl/sqlite
Keywords: sql sqlite sqlite3 database
Platform: UNKNOWN
Classifier: Intended Audience :: Developers
Classifier: License :: OSI Approved :: MIT License
Classifier: Programming Language :: Python :: 3
Classifier: Programming Language :: Python :: 3.6
Classifier: Programming Language :: Python :: 3.7
Classifier: Programming Language :: Python :: 3.8
Classifier: Programming Language :: Python :: 3.9
Classifier: Programming Language :: Python :: 3.10
